interipport.py
interipport-1.1.5.dist-info/LICENSE.txt
interipport-1.1.5.dist-info/METADATA
interipport-1.1.5.dist-info/WHEEL
interipport-1.1.5.dist-info/entry_points.txt
interipport-1.1.5.dist-info/top_level.txt
interipport-1.1.5.dist-info/RECORD
