Metadata-Version: 2.1
Name: interipport
Version: 1.1.5
Summary: A small example package
Home-page: https://github.com/ousyouyou/cyber-security-Ai
Author: OuSyouyou
Author-email: s2122011@stu.musashino-u.ac.jp
Classifier: Programming Language :: Python :: 3
Classifier: License :: OSI Approved :: MIT License
Classifier: Operating System :: OS Independent
Requires-Python: >=3.6
License-File: LICENSE.txt
